tests
sqlalchemy_fileattach
