Metadata-Version: 1.0
Name: sqlalchemy-fileattach
Version: 0.1.3
Summary: UNKNOWN
Home-page: https://github.com/adamcharnock/sqlalchemy-fileattach
Author: Adam Charnock
Author-email: adam@adamcharnock.com
License: MIT
Platform: UNKNOWN
